LICENSE.txt
MANIFEST.in
README.md
setup.cfg
setup.py
matialvarezs_handlers_easy/__init__.py
matialvarezs_handlers_easy/__main__.py
matialvarezs_handlers_easy/admin.py
matialvarezs_handlers_easy/celery_utils.py
matialvarezs_handlers_easy/context_processors.py
matialvarezs_handlers_easy/crontab_jobs_utils.py
matialvarezs_handlers_easy/decorators.py
matialvarezs_handlers_easy/definitions.py
matialvarezs_handlers_easy/dispatcher.py
matialvarezs_handlers_easy/errors.py
matialvarezs_handlers_easy/managers.py
matialvarezs_handlers_easy/middlewares.py
matialvarezs_handlers_easy/models.py
matialvarezs_handlers_easy/mqtt.py
matialvarezs_handlers_easy/mqtthandler_logging.py
matialvarezs_handlers_easy/serializers.py
matialvarezs_handlers_easy/settings.py
matialvarezs_handlers_easy/signals.py
matialvarezs_handlers_easy/urls.py
matialvarezs_handlers_easy/utils.py
matialvarezs_handlers_easy/views.py
matialvarezs_handlers_easy.egg-info/PKG-INFO
matialvarezs_handlers_easy.egg-info/SOURCES.txt
matialvarezs_handlers_easy.egg-info/dependency_links.txt
matialvarezs_handlers_easy.egg-info/requires.txt
matialvarezs_handlers_easy.egg-info/top_level.txt
matialvarezs_handlers_easy/management/__init__.py
matialvarezs_handlers_easy/management/commands/__init__.py
matialvarezs_handlers_easy/management/commands/matialvarezs_handlers_easy_test_command.py